{
    "eCN": "9C",
    "grids": [{
        "gridId": "g1",
        "gridName" : "Grid 1",
        "fields": [{
            "fCN": "9E",
            "order" : 1
        }, {
            "fCN": "9F",
            "order" : 2
        }, {
            "fCN": "9I",
            "order" : 3
        }, {
            "fCN": "9J",
            "order" : 4
        }]
    },{
        "gridId": "g2",
        "gridName" : "Grid 4",
        "fields": [{
            "fCN": "5G",
            "order" : 1
        }, {
            "fCN": "5H",
            "order" : 2
        }, {
            "fCN": "5I",
            "order" : 3
        }, {
            "fCN": "5J",
            "order" : 4
        }]
    },{
        "gridId": "g3",
        "gridName" : "Grid 2",
        "fields": [{
            "fCN": "5G",
            "order" : 1
        }, {
            "fCN": "5H",
            "order" : 2
        }, {
            "fCN": "5I",
            "order" : 3
        }, {
            "fCN": "5J",
            "order" : 4
        }]
    },{
        "gridId": "g4",
        "gridName" : "Grid 3",
        "fields": [{
            "fCN": "5G",
            "order" : 1
        }, {
            "fCN": "5H",
            "order" : 1
        }, {
            "fCN": "5I",
            "order" : 1
        }, {
            "fCN": "5J",
            "order" : 1
        }]
    }]
}